setup.py
rpi_featureSelection/ConditionalMutualInformation.py
rpi_featureSelection/HillClimbing_entropy_discretization.py
rpi_featureSelection/IPCMBplus_selector.py
rpi_featureSelection/JMI_Brute_Force.py
rpi_featureSelection/JMI_selector.py
rpi_featureSelection/JointMutualInformation.py
rpi_featureSelection/Large_Scale_IPCMB.py
rpi_featureSelection/Large_Scale_STMB.py
rpi_featureSelection/MergeArrays.py
rpi_featureSelection/NormaliseArray.py
rpi_featureSelection/STMBplus_selector.py
rpi_featureSelection/calculateConditionalEntropy.py
rpi_featureSelection/calculateJointProbability.py
rpi_featureSelection/coreFunctions.py
rpi_featureSelection/fast_feature_discretization_HC.py
rpi_featureSelection/findOptimalSplitPoint.py
rpi_featureSelection/joint.py
rpi_featureSelection/mutualInformation.py
rpi_featureSelection/tian_IPCMB.py
rpi_featureSelection/tian_RecognizePC_faster.py
rpi_featureSelection/tian_STMB_new.py
rpi_featureSelection/tian_checkDataSize.py
rpi_featureSelection/tian_readData2.py
rpi_featureSelection.egg-info/PKG-INFO
rpi_featureSelection.egg-info/SOURCES.txt
rpi_featureSelection.egg-info/dependency_links.txt
rpi_featureSelection.egg-info/entry_points.txt
rpi_featureSelection.egg-info/requires.txt
rpi_featureSelection.egg-info/top_level.txt