Metadata-Version: 1.0
Name: rpi-featureSelection
Version: 0.0.2
Summary: RPI primitives using the latest 2018.4.18 APIs second submission
Home-page: https://www.ecse.rpi.edu/~cvrl/
Author: Keyi Liu, Zijun Cui, Qiang Ji
Author-email: cuiz3@rpi.edu
License: UNKNOWN
Keywords: d3m_primitive
Platform: Linux
Platform: MacOS
